biorefineries/__init__.py
biorefineries/LAOs/README.rst
biorefineries/LAOs/__init__.py
biorefineries/LAOs/_chemicals.py
biorefineries/LAOs/_process_specifications.py
biorefineries/LAOs/_system.py
biorefineries/LAOs/_tea.py
biorefineries/LAOs/analysis.ipynb
biorefineries/LAOs/chemicals.yaml
biorefineries/LAOs/streams.yaml
biorefineries/LAOs/utils.py
biorefineries/LAOs/units/__init__.py
biorefineries/LAOs/units/adiabatic_fixedbed_gas_reactor.py
biorefineries/LAOs/units/nitrogen_generation_package.py
biorefineries/LAOs/units/surge_tank.py
biorefineries/corn/README.rst
biorefineries/corn/__init__.py
biorefineries/corn/_chemicals.py
biorefineries/corn/_process_settings.py
biorefineries/corn/_system.py
biorefineries/corn/_tea.py
biorefineries/corn/deleteme.xlsx
biorefineries/corn/units.py
biorefineries/corn/utils.py
biorefineries/cornstover/README.rst
biorefineries/cornstover/__init__.py
biorefineries/cornstover/_analysis.py
biorefineries/cornstover/_chemicals.py
biorefineries/cornstover/_humbird2011.xlsx
biorefineries/cornstover/_legacy_code.py
biorefineries/cornstover/_plot_bars.py
biorefineries/cornstover/_plot_spearman.py
biorefineries/cornstover/_plot_uncertainty_top.py
biorefineries/cornstover/_process_settings.py
biorefineries/cornstover/_sankey.py
biorefineries/cornstover/_switchgrass.py
biorefineries/cornstover/_system.py
biorefineries/cornstover/_tea.py
biorefineries/cornstover/model.py
biorefineries/cornstover/specifications.py
biorefineries/cornstover/units.py
biorefineries/cornstover/webapp_model.py
biorefineries/fattyalcohols/README.rst
biorefineries/fattyalcohols/__init__.py
biorefineries/fattyalcohols/_chemicals.py
biorefineries/fattyalcohols/_fattyalcohol_production.py
biorefineries/fattyalcohols/_process_specifications.py
biorefineries/fattyalcohols/_system.py
biorefineries/fattyalcohols/_tea.py
biorefineries/fattyalcohols/chemicals.yaml
biorefineries/fattyalcohols/streams.yaml
biorefineries/fattyalcohols/utils.py
biorefineries-2.23.12.dist-info/LICENSE.txt
biorefineries-2.23.12.dist-info/METADATA
biorefineries-2.23.12.dist-info/WHEEL
biorefineries-2.23.12.dist-info/top_level.txt
biorefineries-2.23.12.dist-info/RECORD
